{
  "type": "Feature",
  "properties": {
    "gn:admin1_code":"0.0",
    "gn:asciiname":"Anse des Flamands",
    "gn:country_code":"BL",
    "gn:dem":9,
    "gn:feature_class":"P",
    "gn:feature_code":"PPL",
    "gn:name":"Anse des Flamands",
    "gn:population":0,
    "gn:timezone":"America/St_Barthelemy",
    "iso:country":"BL",
    "name:und_x_variant":[
        "Quartier des Flamands"
    ],
    "wof:name":"Anse des Flamands",
    "wof:placetype":"locality"
},
  "geometry": {"coordinates":[-62.8575,17.91774],"type":"Point"}
}