{
  "type": "Feature",
  "properties": {
    "iso:country":"BL",
    "name:unk_x_variant":[
        "Quartier du Marigot"
    ],
    "qs:gn_country":"BL",
    "qs:gn_fcode":"PPL",
    "qs:gn_pop":0,
    "qs:name":"Marigot",
    "qs:name_adm0":"Saint-Martin",
    "qs:photos":4997,
    "qs:photos_1k":1000,
    "qs:photos_9k":22,
    "qs:photos_9r":14,
    "qs:photos_all":4997,
    "qs:photos_sr":24,
    "qs:placetype":"Town",
    "qs:pop_sr":"0",
    "qs:woe_adm0":56042305,
    "wd:wordcount":64,
    "wof:name":"Marigot",
    "wof:placetype":"locality"
},
  "geometry": {"coordinates":[-62.81667,17.91667],"type":"Point"}
}